pyotify/__init__.py
pyotify/auth.py
pyotify/client.py
pyotify/main.py
pyotify/utils.py
pyotify-0.0.1.dist-info/LICENSE
pyotify-0.0.1.dist-info/METADATA
pyotify-0.0.1.dist-info/WHEEL
pyotify-0.0.1.dist-info/top_level.txt
pyotify-0.0.1.dist-info/RECORD
