Metadata-Version: 2.1
Name: pyotify
Version: 0.0.1
Summary: Fully-featured library to interact with the Spotify Web API
Home-page: https://github.com/paunzz/pyotify
Author: Bogdan Paunovic
Author-email: bogdanbokipaunovic@gmail.com
License: UNKNOWN
Platform: UNKNOWN
Classifier: Environment :: Console
Classifier: Intended Audience :: Developers
Classifier: Programming Language :: Python :: 3.4
Classifier: Programming Language :: Python :: 3.5
Classifier: Programming Language :: Python :: 3.6
Classifier: Programming Language :: Python :: 3.7
Classifier: Programming Language :: Python :: 3.8
Classifier: Programming Language :: Python :: Implementation :: CPython
Classifier: Programming Language :: Python :: Implementation :: PyPy
Classifier: License :: OSI Approved :: MIT License
Classifier: Operating System :: OS Independent
Requires-Dist: requests (==2.22.0)
Provides-Extra: tests
Requires-Dist: pytest ; extra == 'tests'
